vgis_log/__init__.py
vgis_log/logTools.py
vgis_log-1.0.9.dist-info/METADATA
vgis_log-1.0.9.dist-info/WHEEL
vgis_log-1.0.9.dist-info/top_level.txt
vgis_log-1.0.9.dist-info/RECORD
