Metadata-Version: 2.1
Name: vgis-log
Version: 1.0.9
Summary: A libary for log operator
Home-page: https://github.com/gisfanmachel/vgisLog
Author: gisfanmachel
Author-email: gisfanmachel@gmail.com
License: UNKNOWN
Keywords: log,setuptools,development
Platform: UNKNOWN
Classifier: Development Status :: 3 - Alpha
Classifier: Intended Audience :: Developers
Classifier: Topic :: Software Development :: Build Tools
Classifier: License :: OSI Approved :: MIT License
Classifier: Programming Language :: Python :: 3
Classifier: Programming Language :: Python :: 3.7
Classifier: Programming Language :: Python :: 3.8
Classifier: Programming Language :: Python :: 3.9
Classifier: Programming Language :: Python :: 3.10
Classifier: Programming Language :: Python :: 3 :: Only
Requires-Python: >=3.7, <4
Requires-Dist: vgis-utils
Requires-Dist: loguru
